{
  "objectInfo" : {
    "id" : "0JgopTeiTk2jhgTTujPccg",
    "name" : "Adaptive_iPaaS_SAPActualFile_IDD510028",
    "type" : "PROCESS",
    "metadata" : {
      "modelVersion" : {
        "major" : 1,
        "minor" : 0
      },
      "repoInfo" : {
        "repoHandle" : "pw0VPNzUzeA8rJ4-gt-63877265-2021-01-06T07:23:40.252Z::pd.xml"
      },
      "contextAttributes" : null,
      "additionalInfo" : {
        "description" : "",
        "contentType" : "application/json; charset=utf-8",
        "documentState" : "VALID"
      }
    }
  },
  "dataFileExtension" : "xml",
  "objectRefs" : [ {
    "id" : "aDRS7HHSErDk46llg9riep",
    "name" : "SP_Adaptive_iPaaS_SAPActualFile",
    "type" : "PROCESS",
    "metadata" : {
      "modelVersion" : {
        "major" : 1,
        "minor" : 0
      },
      "repoInfo" : {
        "repoHandle" : "YiPDlyBg7jvpppp-gt-15342373-2021-01-06T07:23:39.813Z::pd.xml"
      },
      "contextAttributes" : null,
      "additionalInfo" : {
        "description" : "",
        "contentType" : "application/json; charset=utf-8",
        "documentState" : "VALID"
      }
    },
    "path" : "/Explore/Global/Adaptive tool integration"
  } ]
}