{
  "objectInfo" : {
    "id" : "hWvl3YIAkEpdJFyx0QnV6Y",
    "name" : "S3Salsify",
    "type" : "AI_CONNECTION",
    "metadata" : {
      "modelVersion" : {
        "major" : 1,
        "minor" : 0
      },
      "repoInfo" : {
        "repoHandle" : "f13ErhNzUzeA8rJ-gt-27254513-2020-08-10T12:40:40.092Z::conn.xml"
      },
      "contextAttributes" : null,
      "additionalInfo" : {
        "description" : "",
        "contentType" : "application/json; charset=utf-8",
        "documentState" : "VALID"
      }
    }
  },
  "dataFileExtension" : "xml",
  "objectRefs" : [ ]
}